neurto/__init__.py
neurto/lfp.py
neurto-0.0.1.dist-info/LICENSE
neurto-0.0.1.dist-info/METADATA
neurto-0.0.1.dist-info/WHEEL
neurto-0.0.1.dist-info/top_level.txt
neurto-0.0.1.dist-info/RECORD
