Metadata-Version: 2.1
Name: neurto
Version: 0.0.1
Summary: TBD... stay tuned
Home-page: https://kwcooper.xyz
Author: Keiland Cooper
Author-email: kwcooper@uci.edu
Project-URL: Documentation, https://github.com/
Project-URL: Bug Reports, https://github.com/
Project-URL: Source Code, https://github.com/
Keywords: neuroscience,toolbox
Classifier: Development Status :: 5 - Production/Stable
Classifier: Intended Audience :: Developers
Classifier: Topic :: Software Development :: Build Tools
Classifier: Programming Language :: Python :: 3
Classifier: Programming Language :: Python :: 3.6
Classifier: Programming Language :: Python :: 3.7
Classifier: Programming Language :: Python :: 3.8
Classifier: Programming Language :: Python :: 3.9
Classifier: Programming Language :: Python :: 3 :: Only
Classifier: License :: OSI Approved :: MIT License
Classifier: Operating System :: OS Independent
Requires-Python: >=3.6
License-File: LICENSE
Provides-Extra: dev
Requires-Dist: check-manifest ; extra == 'dev'
